.gitignore
LICENSE
README.md
environment.yml
setup.cfg
setup.py
bin/gaia2tic
bin/simbad2tic
bin/tic2gaia
cdips/__init__.py
cdips/gyroage.py
cdips/paths.py
cdips/testing.py
cdips.egg-info/PKG-INFO
cdips.egg-info/SOURCES.txt
cdips.egg-info/dependency_links.txt
cdips.egg-info/not-zip-safe
cdips.egg-info/requires.txt
cdips.egg-info/top_level.txt
cdips/DEPRECATED/collect_cluster_lightcurves.py
cdips/DEPRECATED/parse_MWSC.py
cdips/catalogbuild/__init__.py
cdips/catalogbuild/concatenate_merge.py
cdips/catalogbuild/construct_unique_cluster_name_column.py
cdips/catalogbuild/gaia_adql_examples.sql
cdips/catalogbuild/get_hat_gaia_xm.sh
cdips/catalogbuild/homogenize_cluster_lists.py
cdips/catalogbuild/make_unique_name_col.txt
cdips/catalogbuild/membership_lists.py
cdips/catalogbuild/moving_group_xmatch_utils.py
cdips/catalogbuild/nasa_xmatch_utils.py
cdips/catalogbuild/open_cluster_xmatch_utils.py
cdips/catalogbuild/simbad_xmatch_utils.py
cdips/catalogbuild/star_forming_rgn_xmatch_utils.py
cdips/catalogbuild/vizier_xmatch_utils.py
cdips/lcproc/__init__.py
cdips/lcproc/bspline_fit_xyTmag_BIC_approach.py
cdips/lcproc/bspline_fit_xyTmag_crossval.py
cdips/lcproc/detrend.py
cdips/lcproc/find_planets.py
cdips/lcproc/lcmath.py
cdips/lcproc/mask_orbit_edges.py
cdips/lcproc/period_find_for_cluster.py
cdips/lcproc/reformat_lcs_for_mast.py
cdips/lcproc/robust_bspline_regression.py
cdips/lcproc/trex_lc_to_mast_lc.py
cdips/pipetrextuning/__init__.py
cdips/pipetrextuning/optimizing_pipeline_parameters.py
cdips/plotting/__init__.py
cdips/plotting/allvar_report.py
cdips/plotting/lightcurve.py
cdips/plotting/plot_EPD_parameters_vs_time.py
cdips/plotting/plot_before_after_difference_images.py
cdips/plotting/plot_camera_orientations.py
cdips/plotting/plot_catalog_to_gaia_match_statistics.py
cdips/plotting/plot_exoplanetarchive_Rp_vs_P_age_cuts.py
cdips/plotting/plot_mag_vs_EPD_parameters.py
cdips/plotting/plot_quilt_PCs.py
cdips/plotting/plot_quilt_s6_s7.py
cdips/plotting/plot_rms_vs_mag.py
cdips/plotting/plot_showoff_lightcurves_GI_proposal.py
cdips/plotting/plot_star_catalog.py
cdips/plotting/plot_wcsqa.py
cdips/plotting/vetting_pdf.py
