Metadata-Version: 2.1
Name: cdips
Version: 0.4
Summary: Python modules and scripts used for CDIPS project.
Home-page: https://github.com/lgbouma/cdips
Download-URL: https://github.com/lgbouma/cdips/archive/refs/tags/v04.tar.gz
Author: Luke Bouma
Author-email: luke@astro.caltech.edu
License: MIT
Keywords: astronomy
Classifier: Development Status :: 3 - Alpha
Classifier: License :: OSI Approved :: MIT License
Classifier: Intended Audience :: Science/Research
Classifier: Topic :: Scientific/Engineering :: Astronomy
Classifier: Operating System :: OS Independent
Classifier: Programming Language :: Python :: 3
Provides-Extra: all
License-File: LICENSE
